{
  "id": "upk23250",
  "name": "UPK-23-250 Gun pod",
  "description": "The UPK-23 is a late Cold War era gun pod of Soviet origin.\r\n\r\nThe 23 denotes it 23mm caliber and the 250 is it's ammunition capacity.",
  "data": {
    "Range": "Shoer",
    "Guidance": "Unguided",
    "Type": "Gun Pod",
    "Caliber": "23mm",
    "Targets": "Light Armor"
  },
  "aircraft": [
    {
      "instructions": [],
      "id": "mig21bis",
      "name": "MiG-21bis"
    },
    {
      "instructions": [],
      "id": "ka50",
      "name": "Ka-50"
    },
    {
      "instructions": [],
      "id": "mi8mtv2",
      "name": "Mi-8 MTV2"
    }
  ]
}